dse_do_utils/__init__.py
dse_do_utils/cpd25utilities.py
dse_do_utils/datamanager.py
dse_do_utils/deployeddomodel.py
dse_do_utils/deployeddomodelcpd21.py
dse_do_utils/domodeldeployer.py
dse_do_utils/domodelexporter.py
dse_do_utils/mapmanager.py
dse_do_utils/multiscenariomanager.py
dse_do_utils/optimizationengine.py
dse_do_utils/plotly_cpd_workaround.py
dse_do_utils/plotlymanager.py
dse_do_utils/scenariodbmanager.py
dse_do_utils/scenariodbmanager2.py
dse_do_utils/scenariomanager.py
dse_do_utils/scenariopicker.py
dse_do_utils/scenariorunner.py
dse_do_utils/utilities.py
dse_do_utils/version.py
dse_do_utils/__pycache__/__init__.cpython-310.pyc
dse_do_utils/__pycache__/__init__.cpython-311.pyc
dse_do_utils/__pycache__/__init__.cpython-312.pyc
dse_do_utils/__pycache__/datamanager.cpython-310.pyc
dse_do_utils/__pycache__/datamanager.cpython-311.pyc
dse_do_utils/__pycache__/datamanager.cpython-312.pyc
dse_do_utils/__pycache__/optimizationengine.cpython-310.pyc
dse_do_utils/__pycache__/optimizationengine.cpython-311.pyc
dse_do_utils/__pycache__/optimizationengine.cpython-312.pyc
dse_do_utils/__pycache__/scenariomanager.cpython-310.pyc
dse_do_utils/__pycache__/scenariomanager.cpython-311.pyc
dse_do_utils/__pycache__/scenariomanager.cpython-312.pyc
dse_do_utils/__pycache__/utilities.cpython-310.pyc
dse_do_utils/__pycache__/utilities.cpython-311.pyc
dse_do_utils/__pycache__/utilities.cpython-312.pyc
dse_do_utils/__pycache__/version.cpython-310.pyc
dse_do_utils/__pycache__/version.cpython-311.pyc
dse_do_utils/__pycache__/version.cpython-312.pyc
dse_do_utils/core/core01_cpo_optimization_engine.py
dse_do_utils/core/core01_data_manager.py
dse_do_utils/core/core01_db_manager.py
dse_do_utils/core/core01_environment_manager.py
dse_do_utils/core/core01_optimization_engine.py
dse_do_utils/core/core02_data_manager.py
dse_do_utils/core/core02_db_manager.py
dse_do_utils/core/core02_optimization_engine.py
dse_do_utils/core/core02_scenario_runner.py
dse_do_utils-0.5.8.0.dist-info/LICENSE
dse_do_utils-0.5.8.0.dist-info/METADATA
dse_do_utils-0.5.8.0.dist-info/WHEEL
dse_do_utils-0.5.8.0.dist-info/top_level.txt
dse_do_utils-0.5.8.0.dist-info/RECORD
