Metadata-Version: 2.1
Name: dse-do-utils
Version: 0.5.8.0
Summary: Decision Optimization utilities for IBM Cloud Pak for Data projects
Home-page: https://github.com/IBM/dse-decision-optimization-utilities
Author: Victor Terpstra
Author-email: vterpstra@us.ibm.com
License: UNKNOWN
Project-URL: Source, https://github.com/IBM/dse-decision-optimization-utilities
Project-URL: Documentation, https://ibm.github.io/dse-decision-optimization-utilities/
Project-URL: IBM Decision Optimization, https://www.ibm.com/analytics/decision-optimization
Platform: UNKNOWN
Classifier: Development Status :: 4 - Beta
Classifier: Programming Language :: Python :: 3.9
Classifier: License :: OSI Approved :: Apache Software License
Classifier: Operating System :: OS Independent
Classifier: Topic :: Documentation :: Sphinx
